colabdesign/__init__.py
colabdesign/af/__init__.py
colabdesign/af/design.py
colabdesign/af/inputs.py
colabdesign/af/loss.py
colabdesign/af/model.py
colabdesign/af/prep.py
colabdesign/af/utils.py
colabdesign/af/alphafold/__init__.py
colabdesign/af/alphafold/common/__init__.py
colabdesign/af/alphafold/common/confidence.py
colabdesign/af/alphafold/common/protein.py
colabdesign/af/alphafold/common/residue_constants.py
colabdesign/af/alphafold/data/__init__.py
colabdesign/af/alphafold/data/mmcif_parsing.py
colabdesign/af/alphafold/data/parsers.py
colabdesign/af/alphafold/data/pipeline.py
colabdesign/af/alphafold/data/pipeline_multimer.py
colabdesign/af/alphafold/data/prep_inputs.py
colabdesign/af/alphafold/data/tools/__init__.py
colabdesign/af/alphafold/data/tools/utils.py
colabdesign/af/alphafold/model/__init__.py
colabdesign/af/alphafold/model/all_atom.py
colabdesign/af/alphafold/model/all_atom_multimer.py
colabdesign/af/alphafold/model/common_modules.py
colabdesign/af/alphafold/model/config.py
colabdesign/af/alphafold/model/data.py
colabdesign/af/alphafold/model/folding.py
colabdesign/af/alphafold/model/folding_multimer.py
colabdesign/af/alphafold/model/layer_stack.py
colabdesign/af/alphafold/model/lddt.py
colabdesign/af/alphafold/model/mapping.py
colabdesign/af/alphafold/model/model.py
colabdesign/af/alphafold/model/modules.py
colabdesign/af/alphafold/model/modules_multimer.py
colabdesign/af/alphafold/model/prng.py
colabdesign/af/alphafold/model/quat_affine.py
colabdesign/af/alphafold/model/r3.py
colabdesign/af/alphafold/model/utils.py
colabdesign/af/alphafold/model/geometry/__init__.py
colabdesign/af/alphafold/model/geometry/rigid_matrix_vector.py
colabdesign/af/alphafold/model/geometry/rotation_matrix.py
colabdesign/af/alphafold/model/geometry/struct_of_array.py
colabdesign/af/alphafold/model/geometry/test_utils.py
colabdesign/af/alphafold/model/geometry/utils.py
colabdesign/af/alphafold/model/geometry/vector.py
colabdesign/af/alphafold/model/tf/__init__.py
colabdesign-1.1.1.dist-info/METADATA
colabdesign-1.1.1.dist-info/WHEEL
colabdesign-1.1.1.dist-info/top_level.txt
colabdesign-1.1.1.dist-info/RECORD
